trialmesh/__init__.py
trialmesh/cli/__init__.py
trialmesh/cli/download_models.py
trialmesh/cli/run_matcher.py
trialmesh/cli/run_retrieval_pipeline.py
trialmesh/embeddings/__init__.py
trialmesh/embeddings/base.py
trialmesh/embeddings/build_index.py
trialmesh/embeddings/dataset.py
trialmesh/embeddings/factory.py
trialmesh/embeddings/index_builder.py
trialmesh/embeddings/query.py
trialmesh/embeddings/run_embedding.py
trialmesh/embeddings/models/__init__.py
trialmesh/embeddings/models/bge.py
trialmesh/embeddings/models/blue_bert.py
trialmesh/embeddings/models/clinical_bert.py
trialmesh/embeddings/models/e5.py
trialmesh/evaluation/__init__.py
trialmesh/evaluation/evaluate_results.py
trialmesh/fetchers/__init__.py
trialmesh/fetchers/processxml.py
trialmesh/fetchers/pull_sigir2016.py
trialmesh/llm/__init__.py
trialmesh/llm/llama_runner.py
trialmesh/llm/prompt_runner.py
trialmesh/llm/summarizers.py
trialmesh/match/__init__.py
trialmesh/match/matcher.py
trialmesh/utils/__init__.py
trialmesh/utils/codemd.py
trialmesh/utils/prompt_config.py
trialmesh/utils/prompt_registry.py
trialmesh-1.1.0.dist-info/METADATA
trialmesh-1.1.0.dist-info/WHEEL
trialmesh-1.1.0.dist-info/entry_points.txt
trialmesh-1.1.0.dist-info/licenses/LICENSE
trialmesh-1.1.0.dist-info/RECORD
