Metadata-Version: 2.4
Name: trialmesh
Version: 1.1.0
Summary: A modular clinical trial matching system using LLMs and vector search
Project-URL: Homepage, https://github.com/mikeS141618/trialmesh
Project-URL: Bug Tracker, https://github.com/mikeS141618/trialmesh/issues
Project-URL: Documentation, https://github.com/mikeS141618/trialmesh#readme
Author: mikeS141618
License: Apache-2.0
License-File: LICENSE
Keywords: clinical-trials,healthcare,llm,oncology,vector-search
Classifier: Development Status :: 3 - Alpha
Classifier: Intended Audience :: Healthcare Industry
Classifier: Intended Audience :: Science/Research
Classifier: License :: OSI Approved :: Apache Software License
Classifier: Programming Language :: Python :: 3
Classifier: Programming Language :: Python :: 3.12
Classifier: Topic :: Scientific/Engineering :: Medical Science Apps.
Requires-Python: <3.13,>=3.12
Requires-Dist: faiss-cpu==1.11.0
Requires-Dist: matplotlib==3.10.1
Requires-Dist: pandas==2.2.3
Requires-Dist: seaborn==0.13.2
Requires-Dist: vllm==0.8.5
Provides-Extra: dev
Requires-Dist: pytest==8.3.3; extra == 'dev'
